{
	"format_version": "1.8.0",
	"animations": {
		"animation.imposter.idle": {
			"loop": true,
			"animation_length": 0.76,
			"bones": {
				"head": {
					"position": {
						"0.0": {
							"vector": [0, 0, 0]
						},
						"0.4": {
							"vector": [0, -2, 0]
						},
						"0.76": {
							"vector": [0, 0, 0]
						}
					}
				}
			}
		},
		"animation.imposter.run": {
			"loop": true,
			"animation_length": 0.4,
			"bones": {
				"head": {
					"position": {
						"0.0": {
							"vector": [0, 0, 0]
						},
						"0.2": {
							"vector": [0, -2, 0],
							"easing": "easeInOutQuad"
						},
						"0.4": {
							"vector": [0, 0, 0]
						}
					}
				},
				"leg2": {
					"rotation": {
						"0.0": {
							"vector": [25, 0, 0]
						},
						"0.2": {
							"vector": [-25, 0, 0]
						},
						"0.4": {
							"vector": [25, 0, 0]
						}
					}
				},
				"leg1": {
					"rotation": {
						"0.0": {
							"vector": [-25, 0, 0]
						},
						"0.2": {
							"vector": [25, 0, 0]
						},
						"0.4": {
							"vector": [-25, 0, 0]
						}
					}
				}
			}
		}
	},
	"geckolib_format_version": 2
}